PBKDF_PKCS12.py
setup.py
PBKDF_PKCS12.egg-info/PKG-INFO
PBKDF_PKCS12.egg-info/SOURCES.txt
PBKDF_PKCS12.egg-info/dependency_links.txt
PBKDF_PKCS12.egg-info/top_level.txt