Metadata-Version: 1.1
Name: PBKDF-PKCS12
Version: 1.0
Summary: PKCS#12 v1.0 PBKDF Module
Home-page: http://kkoha.tistory.com/entry/Python-PKCS12-v10-PBKDF-Module
Author: koha
Author-email: kkoha@msn.com
License: UNKNOWN
Keywords: PBKDF1,PBKDF2,key derivation,password key derivation,PBKDF,PKCS12,PKCS#12,PKCS,crypto
Platform: UNKNOWN
Classifier: License :: OSI Approved :: MIT License
Classifier: Operating System :: OS Independent
Classifier: Programming Language :: Python :: 2.7
Classifier: Topic :: Security :: Cryptography
